nonebot_plugin_morning/__init__.py
nonebot_plugin_morning/config.py
nonebot_plugin_morning/data_source.py
nonebot_plugin_morning/resource/config.json
nonebot_plugin_morning/utils.py
nonebot_plugin_morning-0.3.1.dist-info/LICENSE
nonebot_plugin_morning-0.3.1.dist-info/WHEEL
nonebot_plugin_morning-0.3.1.dist-info/METADATA
nonebot_plugin_morning-0.3.1.dist-info/RECORD
