Metadata-Version: 2.1
Name: nonebot-plugin-morning
Version: 0.3.1
Summary: Good morning & good night!
License: MIT
Author: KafCoppelia
Author-email: k740677208@gmail.com
Requires-Python: >=3.8,<4.0
Classifier: License :: OSI Approved :: MIT License
Classifier: Programming Language :: Python :: 3
Classifier: Programming Language :: Python :: 3.10
Classifier: Programming Language :: Python :: 3.8
Classifier: Programming Language :: Python :: 3.9
Requires-Dist: nonebot-adapter-onebot (>=2.1.1,<3.0.0)
Requires-Dist: nonebot-plugin-apscheduler (>=0.1.3,<0.2.0)
Requires-Dist: nonebot2 (>=2.0.0b3,<3.0.0)
